causaltorch/__init__.py
causaltorch/config.py
causaltorch/core_architecture.py
causaltorch/layers.py
causaltorch/metrics.py
causaltorch/mlops.py
causaltorch/models.py
causaltorch/rules.py
causaltorch/creative/__init__.py
causaltorch/creative/dreamer.py
causaltorch/ethics/__init__.py
causaltorch/ethics/constitution.py
causaltorch/federated/__init__.py
causaltorch/federated/dao.py
causaltorch/layers/__init__.py
causaltorch/layers/causal_attention.py
causaltorch/layers/causal_linear.py
causaltorch/layers/causal_symbolic.py
causaltorch/layers/meta_learning.py
causaltorch/layers/sparse.py
causaltorch/layers/temporal_causal.py
causaltorch/models/__init__.py
causaltorch/models/image_model.py
causaltorch/models/text_model.py
causaltorch/models/video_model.py
causaltorch/rules/__init__.py
causaltorch/rules/core.py
causaltorch/rules/engine.py
causaltorch/training/__init__.py
causaltorch/training/finetuner.py
causaltorch/training/trainer.py
causaltorch/utils/__init__.py
causaltorch/utils/metrics.py
causaltorch/visualization/__init__.py
causaltorch/visualization/metrics.py
causaltorch/visualization/plot.py
causaltorch-2.1.0.dist-info/licenses/LICENSE
causaltorch-2.1.0.dist-info/METADATA
causaltorch-2.1.0.dist-info/WHEEL
causaltorch-2.1.0.dist-info/top_level.txt
causaltorch-2.1.0.dist-info/RECORD
