Metadata-Version: 2.4
Name: causaltorch
Version: 2.1.0
Summary: A PyTorch library for building generative models with causal constraints
Author-email: Elija Nzeli <elijahnzeli894@example.com>
License-Expression: MIT
Project-URL: Homepage, https://github.com/elijahnzeli1/CausalTorch
Project-URL: Bug Tracker, https://github.com/elijahnzeli1/CausalTorch/issues
Project-URL: Documentation, https://causaltorch.readthedocs.io/
Classifier: Programming Language :: Python :: 3
Classifier: Programming Language :: Python :: 3.7
Classifier: Programming Language :: Python :: 3.8
Classifier: Programming Language :: Python :: 3.9
Classifier: Programming Language :: Python :: 3.10
Classifier: Programming Language :: Python :: 3.11
Classifier: Programming Language :: Python :: 3.12
Classifier: Operating System :: OS Independent
Classifier: Development Status :: 4 - Beta
Classifier: Intended Audience :: Science/Research
Classifier: Intended Audience :: Developers
Classifier: Topic :: Scientific/Engineering :: Artificial Intelligence
Requires-Python: >=3.7
License-File: LICENSE
Requires-Dist: torch>=1.8.0
Requires-Dist: numpy>=1.19.0
Requires-Dist: matplotlib>=3.3.0
Requires-Dist: networkx>=2.5
Requires-Dist: tqdm>=4.61.0
Provides-Extra: text
Requires-Dist: transformers>=4.5.0; extra == "text"
Requires-Dist: tokenizers>=0.10.2; extra == "text"
Provides-Extra: image
Requires-Dist: torchvision>=0.9.0; extra == "image"
Requires-Dist: Pillow>=8.2.0; extra == "image"
Provides-Extra: video
Requires-Dist: av>=8.0.0; extra == "video"
Requires-Dist: opencv-python>=4.5.1; extra == "video"
Provides-Extra: federated
Requires-Dist: pytorch-lightning>=1.3.0; extra == "federated"
Provides-Extra: dev
Requires-Dist: pytest>=6.0.0; extra == "dev"
Requires-Dist: black>=21.5b2; extra == "dev"
Requires-Dist: isort>=5.8.0; extra == "dev"
Requires-Dist: flake8>=3.9.2; extra == "dev"
Requires-Dist: mypy>=0.812; extra == "dev"
Provides-Extra: all
Requires-Dist: transformers>=4.5.0; extra == "all"
Requires-Dist: tokenizers>=0.10.2; extra == "all"
Requires-Dist: torchvision>=0.9.0; extra == "all"
Requires-Dist: Pillow>=8.2.0; extra == "all"
Requires-Dist: av>=8.0.0; extra == "all"
Requires-Dist: opencv-python>=4.5.1; extra == "all"
Requires-Dist: pytorch-lightning>=1.3.0; extra == "all"
Dynamic: license-file
